setup.py
prob_distributions_dsnd/Binomialdistribution.py
prob_distributions_dsnd/Gaussiandistribution.py
prob_distributions_dsnd/Generaldistribution.py
prob_distributions_dsnd/__init__.py
prob_distributions_dsnd.egg-info/PKG-INFO
prob_distributions_dsnd.egg-info/SOURCES.txt
prob_distributions_dsnd.egg-info/dependency_links.txt
prob_distributions_dsnd.egg-info/not-zip-safe
prob_distributions_dsnd.egg-info/top_level.txt