Metadata-Version: 1.0
Name: prob-distributions-dsnd
Version: 1.0
Summary: Gaussian and Binomial distributions
Home-page: UNKNOWN
Author: Truls Møller
Author-email: trullig@gmail.com
License: UNKNOWN
Platform: UNKNOWN
